{"_path":"/articles/2023/fedora_lineageos_sargo","_dir":"2023","_draft":false,"_partial":false,"_locale":"","title":"在Fedora 38編譯Pixel 3a的LineageOS","description":"本篇文章是試圖移植之前的文章：的過程至 Fedora 上的心得紀錄，畢竟自己平常主要使用的系統為 Fedora，想說都是 Linux 應該是可以移植過來。","img":"924/LsYE8j.jpg","tags":["fedora","android","custom rom","Gooel Pixel 3a","lineageos"],"category":"linux","readingTime":{"text":"3 min read","minutes":2.765,"time":165900,"words":553},"excerpt":{"type":"root","children":[{"type":"element","tag":"p","props":{},"children":[{"type":"text","value":"本篇文章是試圖移植之前的文章："},{"type":"element","tag":"article-inner-link","props":{"slug":"ubuntu_lineageos_sargo"},"children":[]},{"type":"text","value":"的過程至 Fedora 上的心得紀錄，畢竟自己平常主要使用的系統為 Fedora，想說都是 Linux 應該是可以移植過來。"}]}]},"body":{"type":"root","children":[{"type":"element","tag":"p","props":{},"children":[{"type":"text","value":"本篇文章是試圖移植之前的文章："},{"type":"element","tag":"article-inner-link","props":{"slug":"ubuntu_lineageos_sargo"},"children":[]},{"type":"text","value":"的過程至 Fedora 上的心得紀錄，畢竟自己平常主要使用的系統為 Fedora，想說都是 Linux 應該是可以移植過來。"}]},{"type":"element","tag":"hr","props":{},"children":[]},{"type":"element","tag":"h2","props":{"id":"硬體需求"},"children":[{"type":"text","value":"硬體需求"}]},{"type":"element","tag":"p","props":{},"children":[{"type":"text","value":"請參考之前的文章："},{"type":"element","tag":"article-inner-link","props":{"slug":"ubuntu_lineageos_sargo"},"children":[]},{"type":"text","value":"。"}]},{"type":"element","tag":"p","props":{},"children":[{"type":"text","value":"不過記憶體的部分，我在 RAM 只有 16GB 的 Fedora，嘗試把 ZRAM 調高到 32GB，仍然會編譯失敗，不知道是不是有什麼其他的眉角需要調整。如果跟我一樣不是很瞭解這些運作機制的話，建議還是直接把電腦記憶體加到 32GB 吧！"}]},{"type":"element","tag":"hr","props":{},"children":[]},{"type":"element","tag":"h2","props":{"id":"建立編譯環境"},"children":[{"type":"text","value":"建立編譯環境"}]},{"type":"element","tag":"h3","props":{"id":"找到-fedora-中的相同套件"},"children":[{"type":"text","value":"找到 Fedora 中的相同套件"}]},{"type":"element","tag":"p","props":{},"children":[{"type":"text","value":"因為官方的教學文件是使用 Ubuntu 編譯，有些編譯需要的套件名稱會不同，首先要做的麻煩事，就是要去把這些套件在 Fedora 中對應的名稱找出來。"}]},{"type":"element","tag":"p","props":{},"children":[{"type":"element","tag":"strong","props":{},"children":[{"type":"text","value":"下面這些列出來的套件對應是自己在網路上搜尋、編譯嘗試錯誤排除以及猜測名稱之後得到的結果，可能可以比這更少，但我不具備這方面的知識，就當作參考吧。"}]}]},{"type":"element","tag":"p","props":{},"children":[{"type":"text","value":"在 Fedora 找不到的套件名稱對應如下，粗體為 Ubuntu 的套件名稱，Fedora 中對應的名稱會用子項目表示："}]},{"type":"element","tag":"ul","props":{},"children":[{"type":"element","tag":"li","props":{},"children":[{"type":"element","tag":"strong","props":{},"children":[{"type":"element","tag":"code","props":{"className":[]},"children":[{"type":"text","value":"build-essential"}]}]},{"type":"text","value":" / "},{"type":"element","tag":"strong","props":{},"children":[{"type":"element","tag":"code","props":{"className":[]},"children":[{"type":"text","value":"g++-multilib"}]}]},{"type":"text","value":" / "},{"type":"element","tag":"strong","props":{},"children":[{"type":"element","tag":"code","props":{"className":[]},"children":[{"type":"text","value":"gcc-multilib"}]}]},{"type":"element","tag":"ul","props":{},"children":[{"type":"element","tag":"li","props":{},"children":[{"type":"element","tag":"code","props":{"className":[]},"children":[{"type":"text","value":"@\"C Development Tools and Libraries\""}]}]},{"type":"element","tag":"li","props":{},"children":[{"type":"element","tag":"code","props":{"className":[]},"children":[{"type":"text","value":"@\"Development Tools\""}]}]},{"type":"element","tag":"li","props":{},"children":[{"type":"element","tag":"code","props":{"className":[]},"children":[{"type":"text","value":"gcc"}]}]},{"type":"element","tag":"li","props":{},"children":[{"type":"element","tag":"code","props":{"className":[]},"children":[{"type":"text","value":"gcc-c++"}]}]},{"type":"element","tag":"li","props":{},"children":[{"type":"element","tag":"code","props":{"className":[]},"children":[{"type":"text","value":"glibc-devel"}]}]},{"type":"element","tag":"li","props":{},"children":[{"type":"element","tag":"code","props":{"className":[]},"children":[{"type":"text","value":"glibc-static"}]}]},{"type":"element","tag":"li","props":{},"children":[{"type":"element","tag":"code","props":{"className":[]},"children":[{"type":"text","value":"libstdc++-devel"}]}]},{"type":"element","tag":"li","props":{},"children":[{"type":"element","tag":"code","props":{"className":[]},"children":[{"type":"text","value":"libstdc++-static"}]}]}]}]},{"type":"element","tag":"li","props":{},"children":[{"type":"element","tag":"strong","props":{},"children":[{"type":"element","tag":"code","props":{"className":[]},"children":[{"type":"text","value":"imagemagick"}]}]},{"type":"element","tag":"ul","props":{},"children":[{"type":"element","tag":"li","props":{},"children":[{"type":"element","tag":"code","props":{"className":[]},"children":[{"type":"text","value":"ImageMagick"}]}]}]}]},{"type":"element","tag":"li","props":{},"children":[{"type":"element","tag":"strong","props":{},"children":[{"type":"element","tag":"code","props":{"className":[]},"children":[{"type":"text","value":"lib32ncurses5-dev"}]}]},{"type":"element","tag":"ul","props":{},"children":[{"type":"element","tag":"li","props":{},"children":[{"type":"element","tag":"code","props":{"className":[]},"children":[{"type":"text","value":"ncurses-devel.i686"}]}]},{"type":"element","tag":"li","props":{},"children":[{"type":"element","tag":"code","props":{"className":[]},"children":[{"type":"text","value":"ncurses-compat-libs.i686"}]}]}]}]},{"type":"element","tag":"li","props":{},"children":[{"type":"element","tag":"strong","props":{},"children":[{"type":"element","tag":"code","props":{"className":[]},"children":[{"type":"text","value":"lib32readline-dev"}]}]},{"type":"element","tag":"ul","props":{},"children":[{"type":"element","tag":"li","props":{},"children":[{"type":"element","tag":"code","props":{"className":[]},"children":[{"type":"text","value":"readline-devel.i686"}]}]}]}]},{"type":"element","tag":"li","props":{},"children":[{"type":"element","tag":"strong","props":{},"children":[{"type":"element","tag":"code","props":{"className":[]},"children":[{"type":"text","value":"lib32z1-dev"}]}]},{"type":"element","tag":"ul","props":{},"children":[{"type":"element","tag":"li","props":{},"children":[{"type":"element","tag":"code","props":{"className":[]},"children":[{"type":"text","value":"zlib-devel.i686"}]}]}]}]},{"type":"element","tag":"li","props":{},"children":[{"type":"element","tag":"strong","props":{},"children":[{"type":"element","tag":"code","props":{"className":[]},"children":[{"type":"text","value":"libelf-dev"}]}]},{"type":"element","tag":"ul","props":{},"children":[{"type":"element","tag":"li","props":{},"children":[{"type":"element","tag":"code","props":{"className":[]},"children":[{"type":"text","value":"elfutils-libelf-devel"}]}]}]}]},{"type":"element","tag":"li","props":{},"children":[{"type":"element","tag":"strong","props":{},"children":[{"type":"element","tag":"code","props":{"className":[]},"children":[{"type":"text","value":"liblz4-tool"}]}]},{"type":"element","tag":"ul","props":{},"children":[{"type":"element","tag":"li","props":{},"children":[{"type":"element","tag":"code","props":{"className":[]},"children":[{"type":"text","value":"lz4-libs"}]}]}]}]},{"type":"element","tag":"li","props":{},"children":[{"type":"element","tag":"strong","props":{},"children":[{"type":"element","tag":"code","props":{"className":[]},"children":[{"type":"text","value":"libncurses5"}]}]},{"type":"element","tag":"ul","props":{},"children":[{"type":"element","tag":"li","props":{},"children":[{"type":"element","tag":"code","props":{"className":[]},"children":[{"type":"text","value":"ncurses-libs"}]}]},{"type":"element","tag":"li","props":{},"children":[{"type":"element","tag":"code","props":{"className":[]},"children":[{"type":"text","value":"ncurses-compat-libs.x86_64"}]}]}]}]},{"type":"element","tag":"li","props":{},"children":[{"type":"element","tag":"strong","props":{},"children":[{"type":"element","tag":"code","props":{"className":[]},"children":[{"type":"text","value":"libncurses5-dev"}]}]},{"type":"element","tag":"ul","props":{},"children":[{"type":"element","tag":"li","props":{},"children":[{"type":"element","tag":"code","props":{"className":[]},"children":[{"type":"text","value":"ncurses-devel.x86_64"}]}]}]}]},{"type":"element","tag":"li","props":{},"children":[{"type":"element","tag":"strong","props":{},"children":[{"type":"element","tag":"code","props":{"className":[]},"children":[{"type":"text","value":"libsdl1.2-dev"}]}]},{"type":"element","tag":"ul","props":{},"children":[{"type":"element","tag":"li","props":{},"children":[{"type":"element","tag":"code","props":{"className":[]},"children":[{"type":"text","value":"sdl12-compat-devel"}]}]}]}]},{"type":"element","tag":"li","props":{},"children":[{"type":"element","tag":"strong","props":{},"children":[{"type":"element","tag":"code","props":{"className":[]},"children":[{"type":"text","value":"libssl-dev"}]}]},{"type":"element","tag":"ul","props":{},"children":[{"type":"element","tag":"li","props":{},"children":[{"type":"element","tag":"code","props":{"className":[]},"children":[{"type":"text","value":"openssl-devel"}]}]}]}]},{"type":"element","tag":"li","props":{},"children":[{"type":"element","tag":"strong","props":{},"children":[{"type":"element","tag":"code","props":{"className":[]},"children":[{"type":"text","value":"libxml2-utils"}]}]},{"type":"element","tag":"ul","props":{},"children":[{"type":"element","tag":"li","props":{},"children":[{"type":"element","tag":"code","props":{"className":[]},"children":[{"type":"text","value":"libxml2-devel"}]}]}]}]},{"type":"element","tag":"li","props":{},"children":[{"type":"element","tag":"strong","props":{},"children":[{"type":"element","tag":"code","props":{"className":[]},"children":[{"type":"text","value":"zlib1g-dev"}]}]},{"type":"element","tag":"ul","props":{},"children":[{"type":"element","tag":"li","props":{},"children":[{"type":"element","tag":"code","props":{"className":[]},"children":[{"type":"text","value":"zlib-devel.x86_64"}]}]}]}]},{"type":"element","tag":"li","props":{},"children":[{"type":"element","tag":"strong","props":{},"children":[{"type":"element","tag":"code","props":{"className":[]},"children":[{"type":"text","value":"openjdk-11-jdk"}]}]},{"type":"element","tag":"ul","props":{},"children":[{"type":"element","tag":"li","props":{},"children":[{"type":"element","tag":"code","props":{"className":[]},"children":[{"type":"text","value":"java-11-openjdk"}]}]}]}]}]},{"type":"element","tag":"h3","props":{"id":"安裝編譯所需套件"},"children":[{"type":"text","value":"安裝編譯所需套件"}]},{"type":"element","tag":"pre","props":{"className":"language-bash shiki shiki-themes github-dark","code":"# 先更新一下系統\nsudo dnf update\n","language":"bash","meta":"","style":""},"children":[{"type":"element","tag":"code","props":{"__ignoreMap":""},"children":[{"type":"element","tag":"span","props":{"class":"line","line":1},"children":[{"type":"element","tag":"span","props":{"style":"--shiki-default:#6A737D"},"children":[{"type":"text","value":"# 先更新一下系統\n"}]}]},{"type":"element","tag":"span","props":{"class":"line","line":2},"children":[{"type":"element","tag":"span","props":{"style":"--shiki-default:#B392F0"},"children":[{"type":"text","value":"sudo"}]},{"type":"element","tag":"span","props":{"style":"--shiki-default:#9ECBFF"},"children":[{"type":"text","value":" dnf"}]},{"type":"element","tag":"span","props":{"style":"--shiki-default:#9ECBFF"},"children":[{"type":"text","value":" update\n"}]}]}]}]},{"type":"element","tag":"pre","props":{"className":"language-bash shiki shiki-themes github-dark","code":"# 安裝編譯需要的套件\nsudo dnf install android-tools bc @\"C Development Tools and Libraries\" @\"Development Tools\" gcc gcc-c++ glibc-devel glibc-static libstdc++-devel libstdc++-static curl git-lfs gnupg gperf ImageMagick ncurses-devel.i686 ncurses-devel.x86_64 ncurses-compat-libs.i686 ncurses-compat-libs.x86_64 readline-devel.i686 zlib-devel.i686 elfutils-libelf-devel lz4-libs ncurses-libs  sdl12-compat-devel openssl-devel libxml2 libxml2-devel lzop pngcrush rsync schedtool squashfs-tools xsltproc zip zlib-devel java-11-openjdk python3 repo wget python3-protobuf -y\n","language":"bash","meta":"","style":""},"children":[{"type":"element","tag":"code","props":{"__ignoreMap":""},"children":[{"type":"element","tag":"span","props":{"class":"line","line":1},"children":[{"type":"element","tag":"span","props":{"style":"--shiki-default:#6A737D"},"children":[{"type":"text","value":"# 安裝編譯需要的套件\n"}]}]},{"type":"element","tag":"span","props":{"class":"line","line":2},"children":[{"type":"element","tag":"span","props":{"style":"--shiki-default:#B392F0"},"children":[{"type":"text","value":"sudo"}]},{"type":"element","tag":"span","props":{"style":"--shiki-default:#9ECBFF"},"children":[{"type":"text","value":" dnf"}]},{"type":"element","tag":"span","props":{"style":"--shiki-default:#9ECBFF"},"children":[{"type":"text","value":" install"}]},{"type":"element","tag":"span","props":{"style":"--shiki-default:#9ECBFF"},"children":[{"type":"text","value":" android-tools"}]},{"type":"element","tag":"span","props":{"style":"--shiki-default:#9ECBFF"},"children":[{"type":"text","value":" bc"}]},{"type":"element","tag":"span","props":{"style":"--shiki-default:#9ECBFF"},"children":[{"type":"text","value":" @\"C Development Tools and Libraries\""}]},{"type":"element","tag":"span","props":{"style":"--shiki-default:#9ECBFF"},"children":[{"type":"text","value":" @\"Development Tools\""}]},{"type":"element","tag":"span","props":{"style":"--shiki-default:#9ECBFF"},"children":[{"type":"text","value":" gcc"}]},{"type":"element","tag":"span","props":{"style":"--shiki-default:#9ECBFF"},"children":[{"type":"text","value":" gcc-c++"}]},{"type":"element","tag":"span","props":{"style":"--shiki-default:#9ECBFF"},"children":[{"type":"text","value":" glibc-devel"}]},{"type":"element","tag":"span","props":{"style":"--shiki-default:#9ECBFF"},"children":[{"type":"text","value":" glibc-static"}]},{"type":"element","tag":"span","props":{"style":"--shiki-default:#9ECBFF"},"children":[{"type":"text","value":" libstdc++-devel"}]},{"type":"element","tag":"span","props":{"style":"--shiki-default:#9ECBFF"},"children":[{"type":"text","value":" libstdc++-static"}]},{"type":"element","tag":"span","props":{"style":"--shiki-default:#9ECBFF"},"children":[{"type":"text","value":" curl"}]},{"type":"element","tag":"span","props":{"style":"--shiki-default:#9ECBFF"},"children":[{"type":"text","value":" git-lfs"}]},{"type":"element","tag":"span","props":{"style":"--shiki-default:#9ECBFF"},"children":[{"type":"text","value":" gnupg"}]},{"type":"element","tag":"span","props":{"style":"--shiki-default:#9ECBFF"},"children":[{"type":"text","value":" gperf"}]},{"type":"element","tag":"span","props":{"style":"--shiki-default:#9ECBFF"},"children":[{"type":"text","value":" ImageMagick"}]},{"type":"element","tag":"span","props":{"style":"--shiki-default:#9ECBFF"},"children":[{"type":"text","value":" ncurses-devel.i686"}]},{"type":"element","tag":"span","props":{"style":"--shiki-default:#9ECBFF"},"children":[{"type":"text","value":" ncurses-devel.x86_64"}]},{"type":"element","tag":"span","props":{"style":"--shiki-default:#9ECBFF"},"children":[{"type":"text","value":" ncurses-compat-libs.i686"}]},{"type":"element","tag":"span","props":{"style":"--shiki-default:#9ECBFF"},"children":[{"type":"text","value":" ncurses-compat-libs.x86_64"}]},{"type":"element","tag":"span","props":{"style":"--shiki-default:#9ECBFF"},"children":[{"type":"text","value":" readline-devel.i686"}]},{"type":"element","tag":"span","props":{"style":"--shiki-default:#9ECBFF"},"children":[{"type":"text","value":" zlib-devel.i686"}]},{"type":"element","tag":"span","props":{"style":"--shiki-default:#9ECBFF"},"children":[{"type":"text","value":" elfutils-libelf-devel"}]},{"type":"element","tag":"span","props":{"style":"--shiki-default:#9ECBFF"},"children":[{"type":"text","value":" lz4-libs"}]},{"type":"element","tag":"span","props":{"style":"--shiki-default:#9ECBFF"},"children":[{"type":"text","value":" ncurses-libs"}]},{"type":"element","tag":"span","props":{"style":"--shiki-default:#9ECBFF"},"children":[{"type":"text","value":"  sdl12-compat-devel"}]},{"type":"element","tag":"span","props":{"style":"--shiki-default:#9ECBFF"},"children":[{"type":"text","value":" openssl-devel"}]},{"type":"element","tag":"span","props":{"style":"--shiki-default:#9ECBFF"},"children":[{"type":"text","value":" libxml2"}]},{"type":"element","tag":"span","props":{"style":"--shiki-default:#9ECBFF"},"children":[{"type":"text","value":" libxml2-devel"}]},{"type":"element","tag":"span","props":{"style":"--shiki-default:#9ECBFF"},"children":[{"type":"text","value":" lzop"}]},{"type":"element","tag":"span","props":{"style":"--shiki-default:#9ECBFF"},"children":[{"type":"text","value":" pngcrush"}]},{"type":"element","tag":"span","props":{"style":"--shiki-default:#9ECBFF"},"children":[{"type":"text","value":" rsync"}]},{"type":"element","tag":"span","props":{"style":"--shiki-default:#9ECBFF"},"children":[{"type":"text","value":" schedtool"}]},{"type":"element","tag":"span","props":{"style":"--shiki-default:#9ECBFF"},"children":[{"type":"text","value":" squashfs-tools"}]},{"type":"element","tag":"span","props":{"style":"--shiki-default:#9ECBFF"},"children":[{"type":"text","value":" xsltproc"}]},{"type":"element","tag":"span","props":{"style":"--shiki-default:#9ECBFF"},"children":[{"type":"text","value":" zip"}]},{"type":"element","tag":"span","props":{"style":"--shiki-default:#9ECBFF"},"children":[{"type":"text","value":" zlib-devel"}]},{"type":"element","tag":"span","props":{"style":"--shiki-default:#9ECBFF"},"children":[{"type":"text","value":" java-11-openjdk"}]},{"type":"element","tag":"span","props":{"style":"--shiki-default:#9ECBFF"},"children":[{"type":"text","value":" python3"}]},{"type":"element","tag":"span","props":{"style":"--shiki-default:#9ECBFF"},"children":[{"type":"text","value":" repo"}]},{"type":"element","tag":"span","props":{"style":"--shiki-default:#9ECBFF"},"children":[{"type":"text","value":" wget"}]},{"type":"element","tag":"span","props":{"style":"--shiki-default:#9ECBFF"},"children":[{"type":"text","value":" python3-protobuf"}]},{"type":"element","tag":"span","props":{"style":"--shiki-default:#79B8FF"},"children":[{"type":"text","value":" -y\n"}]}]}]}]},{"type":"element","tag":"pre","props":{"className":"language-bash shiki shiki-themes github-dark","code":"# 設定git身份(email)\ngit config --global user.email \"you@example.com\"\n","language":"bash","meta":"","style":""},"children":[{"type":"element","tag":"code","props":{"__ignoreMap":""},"children":[{"type":"element","tag":"span","props":{"class":"line","line":1},"children":[{"type":"element","tag":"span","props":{"style":"--shiki-default:#6A737D"},"children":[{"type":"text","value":"# 設定git身份(email)\n"}]}]},{"type":"element","tag":"span","props":{"class":"line","line":2},"children":[{"type":"element","tag":"span","props":{"style":"--shiki-default:#B392F0"},"children":[{"type":"text","value":"git"}]},{"type":"element","tag":"span","props":{"style":"--shiki-default:#9ECBFF"},"children":[{"type":"text","value":" config"}]},{"type":"element","tag":"span","props":{"style":"--shiki-default:#79B8FF"},"children":[{"type":"text","value":" --global"}]},{"type":"element","tag":"span","props":{"style":"--shiki-default:#9ECBFF"},"children":[{"type":"text","value":" user.email"}]},{"type":"element","tag":"span","props":{"style":"--shiki-default:#9ECBFF"},"children":[{"type":"text","value":" \"you@example.com\"\n"}]}]}]}]},{"type":"element","tag":"pre","props":{"className":"language-bash shiki shiki-themes github-dark","code":"# 設定git身份(名稱)\ngit config --global user.name \"Your Name\"\n","language":"bash","meta":"","style":""},"children":[{"type":"element","tag":"code","props":{"__ignoreMap":""},"children":[{"type":"element","tag":"span","props":{"class":"line","line":1},"children":[{"type":"element","tag":"span","props":{"style":"--shiki-default:#6A737D"},"children":[{"type":"text","value":"# 設定git身份(名稱)\n"}]}]},{"type":"element","tag":"span","props":{"class":"line","line":2},"children":[{"type":"element","tag":"span","props":{"style":"--shiki-default:#B392F0"},"children":[{"type":"text","value":"git"}]},{"type":"element","tag":"span","props":{"style":"--shiki-default:#9ECBFF"},"children":[{"type":"text","value":" config"}]},{"type":"element","tag":"span","props":{"style":"--shiki-default:#79B8FF"},"children":[{"type":"text","value":" --global"}]},{"type":"element","tag":"span","props":{"style":"--shiki-default:#9ECBFF"},"children":[{"type":"text","value":" user.name"}]},{"type":"element","tag":"span","props":{"style":"--shiki-default:#9ECBFF"},"children":[{"type":"text","value":" \"Your Name\"\n"}]}]}]}]},{"type":"element","tag":"h3","props":{"id":"確認-java-版本"},"children":[{"type":"text","value":"確認 Java 版本"}]},{"type":"element","tag":"pre","props":{"className":"language-bash shiki shiki-themes github-dark","code":"# 確認Java版本\njava -version\n","language":"bash","meta":"","style":""},"children":[{"type":"element","tag":"code","props":{"__ignoreMap":""},"children":[{"type":"element","tag":"span","props":{"class":"line","line":1},"children":[{"type":"element","tag":"span","props":{"style":"--shiki-default:#6A737D"},"children":[{"type":"text","value":"# 確認Java版本\n"}]}]},{"type":"element","tag":"span","props":{"class":"line","line":2},"children":[{"type":"element","tag":"span","props":{"style":"--shiki-default:#B392F0"},"children":[{"type":"text","value":"java"}]},{"type":"element","tag":"span","props":{"style":"--shiki-default:#79B8FF"},"children":[{"type":"text","value":" -version\n"}]}]}]}]},{"type":"element","tag":"p","props":{},"children":[{"type":"text","value":"若顯示的不是"},{"type":"element","tag":"code","props":{"className":[]},"children":[{"type":"text","value":"openjdk version"}]},{"type":"text","value":"不是"},{"type":"element","tag":"code","props":{"className":[]},"children":[{"type":"text","value":"11"}]},{"type":"text","value":"的話，就要調整。"}]},{"type":"element","tag":"pre","props":{"className":"language-bash shiki shiki-themes github-dark","code":"# 設定Java版本\nsudo alternatives --config java\n","language":"bash","meta":"","style":""},"children":[{"type":"element","tag":"code","props":{"__ignoreMap":""},"children":[{"type":"element","tag":"span","props":{"class":"line","line":1},"children":[{"type":"element","tag":"span","props":{"style":"--shiki-default:#6A737D"},"children":[{"type":"text","value":"# 設定Java版本\n"}]}]},{"type":"element","tag":"span","props":{"class":"line","line":2},"children":[{"type":"element","tag":"span","props":{"style":"--shiki-default:#B392F0"},"children":[{"type":"text","value":"sudo"}]},{"type":"element","tag":"span","props":{"style":"--shiki-default:#9ECBFF"},"children":[{"type":"text","value":" alternatives"}]},{"type":"element","tag":"span","props":{"style":"--shiki-default:#79B8FF"},"children":[{"type":"text","value":" --config"}]},{"type":"element","tag":"span","props":{"style":"--shiki-default:#9ECBFF"},"children":[{"type":"text","value":" java\n"}]}]}]}]},{"type":"element","tag":"pre","props":{"className":"language-bash shiki shiki-themes github-dark","code":"# 會看到像這樣的畫面，要選擇是java-11-openjdk的那條。\n有 2 個程式提供「java」。\n\n  選擇     指令\n-----------------------------------\n*  1       java-17-openjdk.x86_64\n + 2       java-11-openjdk.x86_64\n","language":"bash","meta":"","style":""},"children":[{"type":"element","tag":"code","props":{"__ignoreMap":""},"children":[{"type":"element","tag":"span","props":{"class":"line","line":1},"children":[{"type":"element","tag":"span","props":{"style":"--shiki-default:#6A737D"},"children":[{"type":"text","value":"# 會看到像這樣的畫面，要選擇是java-11-openjdk的那條。\n"}]}]},{"type":"element","tag":"span","props":{"class":"line","line":2},"children":[{"type":"element","tag":"span","props":{"style":"--shiki-default:#B392F0"},"children":[{"type":"text","value":"有"}]},{"type":"element","tag":"span","props":{"style":"--shiki-default:#79B8FF"},"children":[{"type":"text","value":" 2"}]},{"type":"element","tag":"span","props":{"style":"--shiki-default:#9ECBFF"},"children":[{"type":"text","value":" 個程式提供「java」。\n"}]}]},{"type":"element","tag":"span","props":{"class":"line","line":3},"children":[{"type":"element","tag":"span","props":{"emptyLinePlaceholder":true},"children":[{"type":"text","value":"\n"}]}]},{"type":"element","tag":"span","props":{"class":"line","line":4},"children":[{"type":"element","tag":"span","props":{"style":"--shiki-default:#B392F0"},"children":[{"type":"text","value":"  選擇"}]},{"type":"element","tag":"span","props":{"style":"--shiki-default:#9ECBFF"},"children":[{"type":"text","value":"     指令\n"}]}]},{"type":"element","tag":"span","props":{"class":"line","line":5},"children":[{"type":"element","tag":"span","props":{"style":"--shiki-default:#B392F0"},"children":[{"type":"text","value":"-----------------------------------\n"}]}]},{"type":"element","tag":"span","props":{"class":"line","line":6},"children":[{"type":"element","tag":"span","props":{"style":"--shiki-default:#F97583"},"children":[{"type":"text","value":"*"}]},{"type":"element","tag":"span","props":{"style":"--shiki-default:#E1E4E8"},"children":[{"type":"text","value":"  1       java-17-openjdk.x86_64\n"}]}]},{"type":"element","tag":"span","props":{"class":"line","line":7},"children":[{"type":"element","tag":"span","props":{"style":"--shiki-default:#B392F0"},"children":[{"type":"text","value":" +"}]},{"type":"element","tag":"span","props":{"style":"--shiki-default:#79B8FF"},"children":[{"type":"text","value":" 2"}]},{"type":"element","tag":"span","props":{"style":"--shiki-default:#9ECBFF"},"children":[{"type":"text","value":"       java-11-openjdk.x86_64\n"}]}]}]}]},{"type":"element","tag":"pre","props":{"className":"language-bash shiki shiki-themes github-dark","code":"# 再次確認Java版本\njava -version\n","language":"bash","meta":"","style":""},"children":[{"type":"element","tag":"code","props":{"__ignoreMap":""},"children":[{"type":"element","tag":"span","props":{"class":"line","line":1},"children":[{"type":"element","tag":"span","props":{"style":"--shiki-default:#6A737D"},"children":[{"type":"text","value":"# 再次確認Java版本\n"}]}]},{"type":"element","tag":"span","props":{"class":"line","line":2},"children":[{"type":"element","tag":"span","props":{"style":"--shiki-default:#B392F0"},"children":[{"type":"text","value":"java"}]},{"type":"element","tag":"span","props":{"style":"--shiki-default:#79B8FF"},"children":[{"type":"text","value":" -version\n"}]}]}]}]},{"type":"element","tag":"hr","props":{},"children":[]},{"type":"element","tag":"h2","props":{"id":"取得原始碼及編譯"},"children":[{"type":"text","value":"取得原始碼及編譯"}]},{"type":"element","tag":"p","props":{},"children":[{"type":"text","value":"之後步驟由於跟在 Ubuntu 中相同，請參考之前的文章："},{"type":"element","tag":"article-inner-link","props":{"slug":"ubuntu_lineageos_sargo","hash":"取得-lineageos-原始碼"},"children":[]},{"type":"text","value":"。"}]},{"type":"element","tag":"hr","props":{},"children":[]},{"type":"element","tag":"h2","props":{"id":"參考文獻"},"children":[{"type":"text","value":"參考文獻"}]},{"type":"element","tag":"ol","props":{},"children":[{"type":"element","tag":"li","props":{},"children":[{"type":"element","tag":"a","props":{"href":"https://index.ros.org/deps/","rel":["nofollow"]},"children":[{"type":"text","value":"ROS Index"}]}]},{"type":"element","tag":"li","props":{},"children":[{"type":"element","tag":"a","props":{"href":"https://www.pragmaticlinux.com/2022/05/how-to-install-build-essential-on-fedora/","rel":["nofollow"]},"children":[{"type":"text","value":"How to install build-essential on Fedora"}]}]},{"type":"element","tag":"li","props":{},"children":[{"type":"element","tag":"a","props":{"href":"https://docs.fedoraproject.org/en-US/quick-docs/installing-java/#_switching_between_java_versions","rel":["nofollow"]},"children":[{"type":"text","value":"Switching between Java Versions"}]}]},{"type":"element","tag":"li","props":{},"children":[{"type":"element","tag":"a","props":{"href":"https://stackoverflow.com/questions/51698044/libncurses-so-5-cannot-open-shared-library-fedora","rel":["nofollow"]},"children":[{"type":"text","value":"libncurses.so.5 - cannot open shared library, Fedora"}]}]}]},{"type":"element","tag":"style","props":{},"children":[{"type":"text","value":"html .default .shiki span {color: var(--shiki-default);background: var(--shiki-default-bg);font-style: var(--shiki-default-font-style);font-weight: var(--shiki-default-font-weight);text-decoration: var(--shiki-default-text-decoration);}html .shiki span {color: var(--shiki-default);background: var(--shiki-default-bg);font-style: var(--shiki-default-font-style);font-weight: var(--shiki-default-font-weight);text-decoration: var(--shiki-default-text-decoration);}"}]}],"toc":{"title":"","searchDepth":2,"depth":2,"links":[{"id":"硬體需求","depth":2,"text":"硬體需求"},{"id":"建立編譯環境","depth":2,"text":"建立編譯環境","children":[{"id":"找到-fedora-中的相同套件","depth":3,"text":"找到 Fedora 中的相同套件"},{"id":"安裝編譯所需套件","depth":3,"text":"安裝編譯所需套件"},{"id":"確認-java-版本","depth":3,"text":"確認 Java 版本"}]},{"id":"取得原始碼及編譯","depth":2,"text":"取得原始碼及編譯"},{"id":"參考文獻","depth":2,"text":"參考文獻"}]}},"_type":"markdown","_id":"content:articles:2023:fedora_lineageos_sargo.md","_source":"content","_file":"articles/2023/fedora_lineageos_sargo.md","_stem":"articles/2023/fedora_lineageos_sargo","_extension":"md","createdAt":"2023-04-07T09:03:17.000Z","updatedAt":"2023-12-11T10:19:13.000Z","slug":"fedora_lineageos_sargo"}