{"id":"27580f1b-9cf4-45f2-aa2a-19626fd00a0d","timestamp":1717334384952,"matcher":{"static":{"/api/_content/search-1717334384534":{"prerender":true}},"wildcard":{},"dynamic":{}},"prerendered":["/category","/","/category/all/5","/category/frontend/1","/category/linux/1","/category/all/1","/category/life/1","/category/all/3","/category/all/2","/vue_stack_development_devcontainer","/okinawa_fourth_day_2023","/okinawa_foods_2023","/okinawa_first_day_2023","/vue_stack_deployment_pm2","/nuxt2_to_nuxt3_blog_2_settings","/linux_ten_years_experience","/chrome_os_flex_asus_e203na","/fedora_disable_turbo_boost","/buy_me_a_tea","/okinawa_hotel_2023","/nuxt2_to_nuxt3_blog_4_modules_pwa","/nuxt2_to_nuxt3_blog_3_modules_content","/crypto_liquidity_mining_v3","/fedora_zram_resize","/woeusb","/nuxt2_content_git","/fedora_lineageos_sargo","/category/all/4","/pixel3a_custom_rom","/nuxt2_bootstrapvue_treeshaking","/fedora_startup","/nuxt2_to_nuxt3_blog_5_modules_sitemap","/nuxt2_to_nuxt3_blog_0_intro","/nuxt2_to_nuxt3_blog_6_modules_pinia","/nuxt2_to_nuxt3_blog_1_ui","/category/frontend/2","/macbook_air_2013_fedora","/fedora_megasync","/fedora_youtube_download","/nuxt3_vite_pwa","/fedora_unrar","/ubuntu_lineageos_sargo","/category/linux/2","/ubuntu_swap_resize","/fedora_docker_startup","/compare_blog","/okinawa_one_day_tour_bus_2023_south","/okinawa_one_day_tour_bus_2023","/online_survey_money","/crypto_after_ftx","/category/life/2","/free_diving_seeing_friend_black_out_first_time","/crypto_liquidity_mining_v2","/canned_fish_dha_epa","/nuxt2_dynamic_routes_sitemap","/mark_forster","/what_we_know_rainbow_parent","/nuxt2_content_code_block_copy_paste","/mobile_chrome_sticky_bottom","/what_we_know_rainbow_therapy","/collections"]}